dapla_whodat/__init__.py
dapla_whodat/client/client.py
dapla_whodat/client/response_errors.py
dapla_whodat/constants.py
dapla_whodat/model.py
dapla_whodat/py.typed
dapla_whodat/result.py
dapla_whodat/utils.py
dapla_whodat/whodat.py
dapla_toolbelt_whodat-1.2.1.dist-info/WHEEL
dapla_toolbelt_whodat-1.2.1.dist-info/entry_points.txt
dapla_toolbelt_whodat-1.2.1.dist-info/METADATA
dapla_toolbelt_whodat-1.2.1.dist-info/RECORD
