Metadata-Version: 2.4
Name: dapla-toolbelt-whodat
Version: 1.2.1
Summary: Whodat
Author: Team Statistikktjenester
Author-email: Team Statistikktjenester <contact-email@ssb.no>
License-Expression: MIT
Classifier: Programming Language :: Python :: 3
Classifier: Programming Language :: Python :: 3.10
Classifier: Programming Language :: Python :: 3.11
Classifier: Programming Language :: Python :: 3.12
Classifier: Programming Language :: Python :: 3.13
Classifier: License :: OSI Approved :: MIT License
Classifier: Development Status :: 4 - Beta
Classifier: Typing :: Typed
Requires-Dist: aiohttp>=3.12.15
Requires-Dist: aiohttp-retry>=2.9.1
Requires-Dist: click>=8.0.1
Requires-Dist: dapla-auth-client>=1.1.0
Requires-Dist: pandas>=2.3.2
Requires-Dist: pandas-stubs>=2.3.2.250827
Requires-Dist: polars<=2.0.0
Requires-Dist: pyarrow>=21.0.0
Requires-Dist: pydantic>=2.11.7
Requires-Dist: pytest>=8.4.1
Requires-Dist: pytest-cases>=3.9.1
Requires-Dist: pytest-xdist[psutil]>=3.8.0
Requires-Dist: python-ulid>=3.1.0
Requires-Dist: requests>=2.32.5
Maintainer: Statistics Norway, Data enablement Department (724)
Requires-Python: >=3.10, <4.0
Project-URL: Changelog, https://github.com/statisticsnorway/dapla-toolbelt-whodat/releases
Project-URL: documentation, https://statisticsnorway.github.io/dapla-toolbelt-whodat
Project-URL: homepage, https://github.com/statisticsnorway/dapla-toolbelt-whodat
Project-URL: repository, https://github.com/statisticsnorway/dapla-toolbelt-whodat
